{"version":1,"resource":"file:///home/pyturtle_/Documents/ESHOPPING/ecommerce/store/static/css/product.css","entries":[{"id":"Uz6u.css","timestamp":1687608658074},{"id":"XBK0.css","timestamp":1687609270510},{"id":"L2A2.css","source":"moved.source","timestamp":1687609507227},{"id":"ABtx.css","timestamp":1687609677402},{"id":"etl3.css","timestamp":1687609711495},{"id":"8xSG.css","timestamp":1687609722889},{"id":"pLu0.css","timestamp":1687609741852},{"id":"d5qr.css","timestamp":1687609773788},{"id":"go8U.css","timestamp":1687609786205},{"id":"plY5.css","timestamp":1687609799034},{"id":"aEBv.css","timestamp":1687609817158},{"id":"Avcw.css","timestamp":1687609899990},{"id":"kY3K.css","timestamp":1687610130797},{"id":"vZKE.css","timestamp":1687610144060},{"id":"vtnC.css","timestamp":1687610307209},{"id":"SceC.css","timestamp":1687610345408},{"id":"peOy.css","timestamp":1687610362155},{"id":"i9Cx.css","timestamp":1687610377001},{"id":"frpz.css","timestamp":1690635194131},{"id":"3Mqq.css","timestamp":1690635861505},{"id":"7Fk2.css","timestamp":1690636103412},{"id":"eDai.css","timestamp":1690636285955},{"id":"IUeX.css","timestamp":1690636374281},{"id":"y5WI.css","timestamp":1691829493699},{"id":"N7mh.css","timestamp":1691829535202},{"id":"5xvi.css","timestamp":1691829554842}]}